Workbook

Sheet Samenvatting
A1: SmartPaw VOF — kwartaalpakket Q4 2026
A2: Voorbereid door het SmartPaw-financiënplatform op 2026-10-27. Voorbereiding: Pro-count controleert en dient in.
A4: Verkopen Shopify (netto excl. btw) | B4: =Verkopen!F8
A5: Verkopen bol.com (netto excl. btw) | B5: =Verkopen!D15
A6: Btw op verkopen (vak 54) | B6: ='Btw-voorbereiding'!C5
A7: Aftrekbare btw (vak 59) | B7: ='Btw-voorbereiding'!C11
A8: Te betalen volgens voorbereiding | B8: ='Btw-voorbereiding'!C12
A9: Te betalen volgens Pro-count | B9: ='Btw-voorbereiding'!C13
A10: Verschil | B10: ='Btw-voorbereiding'!C14
A11: Uitgaven met onzekere btw-behandeling (NAKIJKEN) | B11: =COUNTIF(Aankopen!E4:E28,"NAKIJKEN")
A12: Verrichtingen zonder bewijs | B12: 12
A14: Tabbladen: Verkopen · Aankopen · Btw-voorbereiding · Bankafstemming · Documenten · Leningen · OSS

Sheet Verkopen
A1: Verkopen Q4 2026 (Shopify per factuurland + bol.com)
A3: Shopify – land | B3: Orders | C3: Bruto | D3: Korting | E3: Retours | F3: Netto excl. btw | G3: Verzending (incl. btw) | H3: Btw | I3: Totaal incl. btw
A4: België | B4: 121 | C4: 11413.24 | D4: -1681.78 | E4: -440.57 | F4: 9290.89 | G4: 52.11 | H4: 1920.66 | I4: 11263.66
A5: Nederland | B5: 13 | C5: 974.66 | D5: -160.99 | E5: -250.06 | F5: 563.61 | G5: 14.88 | H5: 121.47 | I5: 699.96
A6: (geen land ingevuld) | B6: 3 | C6: 128.99 | D6: -128.99 | E6: 0 | F6: 0 | G6: 0 | H6: 0 | I6: 0
A7: Portugal | B7: 1 | C7: 19.82 | D7: 0 | E7: 0 | F7: 19.82 | G7: 5.79 | H7: 5.37 | I7: 30.98
A8: Totaal Shopify | B8: =SUM(B4:B7) | C8: =SUM(C4:C7) | D8: =SUM(D4:D7) | E8: =SUM(E4:E7) | F8: =SUM(F4:F7) | G8: =SUM(G4:G7) | H8: =SUM(H4:H7) | I8: =SUM(I4:I7)
A10: bol.com (uit de bol-facturen)
A11: bol – maand | B11: Orders | C11: Omzet incl. btw (na retouren) | D11: Netto excl. btw | E11: Btw 21% | F11: Commissie (kost, verlegd) | G11: bol-ads (kost) | H11: Retourlabels (kost)
A12: 2026-10 | B12: 0 | C12: 0 | D12: =C12/1.21 | E12: =C12-D12 | F12: 0 | G12: 0 | H12: 0
A13: 2026-11 | B13: 0 | C13: 0 | D13: =C13/1.21 | E13: =C13-D13 | F13: 0 | G13: 0 | H13: 0
A14: 2026-12 | B14: 0 | C14: 0 | D14: =C14/1.21 | E14: =C14-D14 | F14: 0 | G14: 0 | H14: 0
A15: Totaal bol | B15: =SUM(B12:B14) | C15: =SUM(C12:C14) | D15: =SUM(D12:D14) | E15: =SUM(E12:E14) | F15: =SUM(F12:F14) | G15: =SUM(G12:G14) | H15: =SUM(H12:H14)
A17: Per betaalwijze (Shopify)
A18: Betaalwijze | B18: Bruto | C18: Terugbetaald | D18: Netto
A19: Shopify Payments (kaart, Bancontact, Klarna, …) | B19: 12871.33 | C19: -876.73 | D19: 11994.6
A21: Shopify Payments-kosten (fees) | D21: 185.4
A22: Verwachte uitbetalingen (netto − fees) | D22: =D19-D21
A23: Stortingen Shopify Payments op KBC in dit kwartaal | D23: 7891.52
A24: Verschil (timing: verkoop eind vorig kwartaal betaald in dit kwartaal, en omgekeerd) | D24: =D23-D22

Sheet Aankopen
A1: Uitgaven Q4 2026 volgens de bank (KBC, KBC-kredietkaart, Revolut) — met btw-behandeling
A3: Datum | B3: Rekening | C3: Leverancier | D3: Categorie | E3: Btw-type | F3: Vak aangifte | G3: Toelichting | H3: Betaald (incl. btw) | I3: Maatstaf (excl. btw) | J3: Btw
A4: 2026-10-01 | B4: KBC | C4: Yuki Works NV via Mollie | D4: Software & abonnementen | E4: BE21 | F4: 82 (+ btw in 59) | G4: Belgische leverancier | H4: 2.42 | I4: =H4/1.21 | J4: =H4-I4
A5: 2026-10-01 | B5: KBC | C5: GOOGLE*WORKSPACE SMART IED02 R296 CC GOOGLE.C | D5: Software & abonnementen | E5: EU | F5: 88 / 55 / 59 | G5: dienst Ierland/EU, verlegd | H5: 75.9 | I5: =H5 | J5: =I5*0.21
A6: 2026-10-01 | B6: KBC-kaart | C6: METAPAY*MV4B | D6: Ads Meta | E6: EU | F6: 88 / 55 / 59 | G6: dienst Ierland/EU, verlegd | H6: 22.29 | I6: =H6 | J6: =I6*0.21
A7: 2026-10-03 | B7: KBC-kaart | C7: ALIBABA.COM | D7: Voorraad (fabriek) | E7: INVOER | F7: invoeraangifte (Widem) | G7: goederen China; btw via invoer (Widem) | H7: 333 | I7: =H7 | J7: 0
A8: 2026-10-04 | B8: KBC | C8: FACEBK *QVA4B7E8A4 IED04 X2K5 DUBLIN Betaling | D8: Ads Meta | E8: EU | F8: 88 / 55 / 59 | G8: dienst Ierland/EU, verlegd | H8: 800 | I8: =H8 | J8: =I8*0.21
A9: 2026-10-05 | B9: KBC | C9: Pro-Count | D9: Boekhouder | E9: BE21 | F9: 82 (+ btw in 59) | G9: Belgische leverancier | H9: 242 | I9: =H9/1.21 | J9: =H9-I9
A10: 2026-10-08 | B10: Revolut | C10: Company Pro plan fee | D10: Software & abonnementen | E10: GEEN | F10: 82 zonder btw | G10: vrijgesteld / geen btw | H10: 35 | I10: =H10 | J10: 0
A11: 2026-10-08 | B11: KBC | C11: FACEBK *MYTGS7E8A4 IED04 X2K5 DUBLIN Betaling | D11: Ads Meta | E11: EU | F11: 88 / 55 / 59 | G11: dienst Ierland/EU, verlegd | H11: 517.01 | I11: =H11 | J11: =I11*0.21
A12: 2026-10-08 | B12: KBC-kaart | C12: HOLO AI | D12: Marketing & content | E12: EU | F12: 88 / 55 / 59 | G12: dienst Ierland/EU, verlegd | H12: 42.95 | I12: =H12 | J12: =I12*0.21
A13: 2026-10-09 | B13: KBC-kaart | C13: SHOPIFY* 601792977 | D13: Software & abonnementen | E13: EU | F13: 88 / 55 / 59 | G13: dienst Ierland/EU, verlegd | H13: 129.2 | I13: =H13 | J13: =I13*0.21
A14: 2026-10-10 | B14: KBC-kaart | C14: KLAVIYO INC. SOFTWARE | D14: Software & abonnementen | E14: NONEU | F14: 87 / 56 / 59 | G14: dienst buiten EU, verlegd | H14: 63.59 | I14: =H14 | J14: =I14*0.21
A15: 2026-10-10 | B15: KBC-kaart | C15: GODADDY*#7038004865 | D15: Software & abonnementen | E15: NONEU | F15: 87 / 56 / 59 | G15: dienst buiten EU, verlegd | H15: 167.76 | I15: =H15 | J15: =I15*0.21
A16: 2026-10-11 | B16: KBC | C16: FACEBK *XX3GC6J8A4 IED04 X2K5 DUBLIN Betaling | D16: Ads Meta | E16: EU | F16: 88 / 55 / 59 | G16: dienst Ierland/EU, verlegd | H16: 800 | I16: =H16 | J16: =I16*0.21
A17: 2026-10-14 | B17: KBC-kaart | C17: ALIBABA.COM | D17: Voorraad (fabriek) | E17: INVOER | F17: invoeraangifte (Widem) | G17: goederen China; btw via invoer (Widem) | H17: 779.1 | I17: =H17 | J17: 0
A18: 2026-10-15 | B18: KBC | C18: HIGGSFIELD INC. US94105 SAN FRANCISCO Betalin | D18: Marketing & content | E18: NONEU | F18: 87 / 56 / 59 | G18: dienst buiten EU, verlegd | H18: 67.84 | I18: =H18 | J18: =I18*0.21
A19: 2026-10-15 | B19: KBC | C19: FACEBK *J3XKX8W7A4 IED04 X2K5 DUBLIN Betaling | D19: Ads Meta | E19: EU | F19: 88 / 55 / 59 | G19: dienst Ierland/EU, verlegd | H19: 800 | I19: =H19 | J19: =I19*0.21
A20: 2026-10-15 | B20: KBC | C20: SMARTPAW VOF | D20: Aflossing KBC-krediet | E20: FIN | F20: — | G20: geen aankoop | H20: 530.4 | I20: =H20 | J20: 0
A21: 2026-10-15 | B21: KBC | C21: SMARTPAW VOF | D21: Rente KBC-krediet | E21: GEEN | F21: 82 zonder btw | G21: vrijgesteld / geen btw | H21: 58.47 | I21: =H21 | J21: 0
A22: 2026-10-15 | B22: KBC | C22: HIGGSFIELD INC. US94105 SAN FRANCISCO Betalin | D22: Marketing & content | E22: NONEU | F22: 87 / 56 / 59 | G22: dienst buiten EU, verlegd | H22: 36.2 | I22: =H22 | J22: =I22*0.21
A23: 2026-10-18 | B23: KBC | C23: FACEBK *U6Y6G7J7A4 IED04 X2K5 DUBLIN Betaling | D23: Ads Meta | E23: EU | F23: 88 / 55 / 59 | G23: dienst Ierland/EU, verlegd | H23: 800 | I23: =H23 | J23: =I23*0.21
A24: 2026-10-19 | B24: KBC | C24: HIGGSFIELD INC. US94105 SAN FRANCISCO Betalin | D24: Marketing & content | E24: NONEU | F24: 87 / 56 / 59 | G24: dienst buiten EU, verlegd | H24: 72 | I24: =H24 | J24: =I24*0.21
A25: 2026-10-20 | B25: KBC | C25: BPOST NV BE1000 BRUXELLES Betaling met KBC-De | D25: Verzending & retours (overig) | E25: BE21 | F25: 82 (+ btw in 59) | G25: Belgische leverancier | H25: 6.78 | I25: =H25/1.21 | J25: =H25-I25
A26: 2026-10-21 | B26: KBC | C26: FACEBK *L8VFT7J8A4 IED04 X2K5 DUBLIN Betaling | D26: Ads Meta | E26: EU | F26: 88 / 55 / 59 | G26: dienst Ierland/EU, verlegd | H26: 800 | I26: =H26 | J26: =I26*0.21
A27: 2026-10-23 | B27: KBC-kaart | C27: FACEBK *CNGZB8S7A4 | D27: Ads Meta | E27: EU | F27: 88 / 55 / 59 | G27: dienst Ierland/EU, verlegd | H27: 621.34 | I27: =H27 | J27: =I27*0.21
A28: 2026-10-25 | B28: KBC | C28: bpost parcel | D28: Verzending & retours (overig) | E28: BE21 | F28: 82 (+ btw in 59) | G28: Belgische leverancier | H28: 8.6 | I28: =H28/1.21 | J28: =H28-I28

Sheet Btw-voorbereiding
A1: Btw-aangifte Q4 2026 — voorbereiding (ter controle door Pro-count)
A3: Vak | B3: Omschrijving | C3: Bedrag
A4: 03 | B4: Verkopen 21% (maatstaf): Shopify netto + verzending excl. btw + bol netto | C4: =Verkopen!F8+Verkopen!G8/1.21+Verkopen!D15
A5: 54 | B5: Verschuldigde btw op verkopen | C5: =Verkopen!H8+Verkopen!E15
A6: 82 | B6: Aankopen diensten en diverse goederen BE (maatstaf, incl. niet-aftrekbaar) | C6: =SUMIFS(Aankopen!$I$4:$I$28,Aankopen!$E$4:$E$28,"BE21")+SUMIFS(Aankopen!$I$4:$I$28,Aankopen!$E$4:$E$28,"BE21NA")+SUMIFS(Aankopen!$I$4:$I$28,Aankopen!$E$4:$E$28,"GEEN")
A7: 88 | B7: Diensten uit andere EU-landen (verlegd) — maatstaf | C7: =SUMIFS(Aankopen!$I$4:$I$28,Aankopen!$E$4:$E$28,"EU")
A8: 55 | B8: Btw op vak 88 (verlegd, verschuldigd) | C8: =SUMIFS(Aankopen!$J$4:$J$28,Aankopen!$E$4:$E$28,"EU")
A9: 87 | B9: Diensten van buiten de EU (verlegd) + invoer art. 41 — maatstaf | C9: =SUMIFS(Aankopen!$I$4:$I$28,Aankopen!$E$4:$E$28,"NONEU")+0
A10: 56 | B10: Btw op vak 87 (verlegd, verschuldigd) | C10: =SUMIFS(Aankopen!$J$4:$J$28,Aankopen!$E$4:$E$28,"NONEU")
A11: 59 | B11: Aftrekbare btw: Belgische aankopen 21% + verlegde btw 55 + 56 + 57 | C11: =SUMIFS(Aankopen!$J$4:$J$28,Aankopen!$E$4:$E$28,"BE21")+C8+C10+C15
B12: Te betalen (54 + 55 + 56 + 57 − 59) | C12: =C5+C8+C10+C15-C11
B13: Opgegeven door Pro-count (mail 22/10/2026) | C13: 6873.24
B14: Verschil voorbereiding − Pro-count | C14: =C12-C13
A15: 57 | B15: Btw op invoer met verlegging (art. 41, invoeraangiftes Widem) | C15: 0
A16: Niet in deze voorbereiding: btw-correcties, en uitgaven van het type 'NAKIJKEN' (zie Aankopen).
A17: Invoer: waarde onbekend voor WID202608397 (invoeraangifte opvragen bij Widem); 57 en 59 heffen elkaar op.
A18: Ook alle NL-verkopen dragen nu Belgische btw (OSS-drempel €10.000 nog niet bereikt, zie OSS).

Sheet Bankafstemming
A1: Bankafstemming Q4 2026
A3: Rekening | B3: Munt | C3: Beginsaldo | D3: In | E3: Uit | F3: Eindsaldo | G3: Verrichtingen | H3: Controle (moet 0 zijn)
A4: KBC zichtrekening BE84 7310 7076 0259 | B4: EUR | C4: -331.19 | D4: 8962.11 | E4: -6467.34 | F4: 2163.58 | G4: 34 | H4: =C4+D4+E4-F4
A5: Revolut Business EUR | B5: EUR | C5: 0 | D5: 35 | E5: -35 | F5: 0 | G5: 2 | H5: =C5+D5+E5-F5
A6: Revolut Business USD | B6: USD | C6: 569.84 | D6: 0 | E6: -39.15 | F6: 530.69 | G6: 1 | H6: =C6+D6+E6-F6
A8: Saldi teruggerekend vanaf de bankstand van 2026-10-27 (Ponto/Revolut). KBC-kredietkaart: zie Aankopen (rekening 'KBC-kaart'); afrekening via de zichtrekening.
A9: Kredietkaartuitgaven in dit kwartaal | F9: 2159.23

Sheet Documenten
A1: Bewijs per verrichting: 11 gekoppeld, 18 verklaard (geen factuur nodig, niet in deze lijst), 12 ontbreken. Facturen zitten in de map Facturen_Q4-2026 (bestandsnaam = datum_leverancier_bedrag).
A3: Datum | B3: Tegenpartij | C3: Bedrag | D3: Btw-type | E3: Status | F3: Bewijs
A4: 2026-10-01 | B4: Yuki Works NV via Mollie | C4: -2.42 | D4: BE21 | E4: ontbreekt
A5: 2026-10-01 | B5: GOOGLE*WORKSPACE SMART IED02 R296 CC GOOGLE.COM Be | C5: -75.9 | D5: EU | E5: ontbreekt
A6: 2026-10-01 | B6: METAPAY*MV4B | C6: -22.29 | D6: EU | E6: ontbreekt
A7: 2026-10-05 | B7: Pro-Count | C7: -242 | D7: BE21 | E7: ontbreekt
A8: 2026-10-08 | B8: Company Pro plan fee | C8: -35 | D8: GEEN | E8: ontbreekt
A9: 2026-10-10 | B9: KLAVIYO INC. SOFTWARE | C9: -63.59 | D9: NONEU | E9: ontbreekt
A10: 2026-10-10 | B10: GODADDY*#7038004865 | C10: -167.76 | D10: NONEU | E10: ontbreekt
A11: 2026-10-15 | B11: HIGGSFIELD INC. US94105 SAN FRANCISCO Betaling met | C11: -67.84 | D11: NONEU | E11: ontbreekt
A12: 2026-10-15 | B12: HIGGSFIELD INC. US94105 SAN FRANCISCO Betaling met | C12: -36.2 | D12: NONEU | E12: ontbreekt
A13: 2026-10-19 | B13: HIGGSFIELD INC. US94105 SAN FRANCISCO Betaling met | C13: -72 | D13: NONEU | E13: ontbreekt
A14: 2026-10-20 | B14: BPOST NV BE1000 BRUXELLES Betaling met KBC-Debetka | C14: -6.78 | D14: BE21 | E14: ontbreekt
A15: 2026-10-23 | B15: FACEBK *CNGZB8S7A4 | C15: -621.34 | D15: EU | E15: ontbreekt
A16: 2026-10-03 | B16: ALIBABA.COM | C16: -333 | D16: INVOER | E16: gekoppeld | F16: Alibaba-ontvangstbewijs order 33333736501041123 (filters FF007 250 + FF009L 240)
A17: 2026-10-04 | B17: FACEBK *QVA4B7E8A4 IED04 X2K5 DUBLIN Betaling met | C17: -800 | D17: EU | E17: gekoppeld | F17: Meta-kwitantie 28560783836940336-28560783956940324 (2026-10-04) – in Lucy/Yuki
A18: 2026-10-08 | B18: FACEBK *MYTGS7E8A4 IED04 X2K5 DUBLIN Betaling met | C18: -517.01 | D18: EU | E18: gekoppeld | F18: Meta-kwitantie 28823801243971925-28794383930246982 (2026-10-08) – in Lucy/Yuki
A19: 2026-10-08 | B19: HOLO AI | C19: -42.95 | D19: EU | E19: gekoppeld | F19: Holo AI HOLO-202610-DB395
A20: 2026-10-09 | B20: SHOPIFY* 601792977 | C20: -129.2 | D20: EU | E20: gekoppeld | F20: Shopify-factuur 601792977 (mail 9/10)
A21: 2026-10-11 | B21: FACEBK *XX3GC6J8A4 IED04 X2K5 DUBLIN Betaling met | C21: -800 | D21: EU | E21: gekoppeld | F21: Meta-kwitantie 28770796055939105-28874006408951408 (2026-10-11) – in Lucy/Yuki
A22: 2026-10-14 | B22: ALIBABA.COM | C22: -779.1 | D22: INVOER | E22: gekoppeld | F22: Alibaba-ontvangstbewijs order 33333736501041123 (filters FF007 250 + FF009L 240)
A23: 2026-10-15 | B23: FACEBK *J3XKX8W7A4 IED04 X2K5 DUBLIN Betaling met | C23: -800 | D23: EU | E23: gekoppeld | F23: Meta-kwitantie 28719082304443821-28719082454443806 (2026-10-14) – in Lucy/Yuki
A24: 2026-10-18 | B24: FACEBK *U6Y6G7J7A4 IED04 X2K5 DUBLIN Betaling met | C24: -800 | D24: EU | E24: gekoppeld | F24: Meta-kwitantie 28824246560594057-28961227476895959 (2026-10-18) – in Lucy/Yuki
A25: 2026-10-21 | B25: FACEBK *L8VFT7J8A4 IED04 X2K5 DUBLIN Betaling met | C25: -800 | D25: EU | E25: gekoppeld | F25: Meta-kwitantie 28937478365937539-29039294869089227 (2026-10-21) – in Lucy/Yuki
A26: 2026-10-25 | B26: bpost parcel | C26: -8.6 | D26: BE21 | E26: gekoppeld | F26: bpost-bestelling 12897185 (26/10)

Sheet Leningen
A1: Leningen en rekening-courant op 2026-12-31 (uit de bank; voorwaarden te bevestigen)
A3: Lening | B3: Opgenomen | C3: Afgelost | D3: Saldo | E3: Rente betaald | F3: Uitleg
A4: KBC investeringskrediet 420-695088 | B4: 19947 | C4: 2628.54 | D4: 17318.46 | E4: 509.66 | F4: 36 mnd vanaf 15/02/2026, rente ±4,1% (bevestigen met kredietvoorstel); kapitaal en rente apart uit de maandelijkse betalingen
A5: Creazy CommV (vennootschap Kaydee) | B5: 11176.42 | C5: 1176.42 | D5: 10000 | E5: 0 | F5: 24/06 €10.000 lening + 25/05 €435,72 (reden?) ; 22/01 €1.176,42 = terugstorting btw die SmartPaw op 18/01 voor Creazy betaalde (verrekend)
A6: Lening Kaydee | B6: 9000 | C6: 9000 | D6: 0 | E6: 0 | F6: €9.000 op 05/02 (Revolut), terug op 18/02. Nieuwe lening met intrest? → bevestigen
A7: Rekening-courant Henri (voorraad uit inbreng jan 2024) | B7: 14000 | C7: 0 | D7: 14000 | E7: 0 | F7: oprichting / inbreng; voorwaarden, rente?

Sheet OSS
A1: Verkoop op afstand aan particulieren in andere EU-landen — drempel €10.000 per kalenderjaar (alle EU-landen samen, excl. btw)
A3: 2025 (VOF, okt-dec)
A4: Nederland | B4: 746.62
A5: Frankrijk | B5: 1712
A6: Portugal | B6: 24.79
A7: Totaal | B7: =SUM(B4:B6) | C7: =IF(B7>10000,"DREMPEL OVERSCHREDEN: btw van het land van de klant via OSS","onder de drempel: Belgische btw")
A9: 2026 (t/m 26/10)
A10: Nederland | B10: 5911.04
A11: Frankrijk | B11: 13.08
A12: Luxemburg | B12: 117.54
A13: Portugal | B13: 19.82
A14: Totaal | B14: =SUM(B10:B13) | C14: =IF(B14>10000,"DREMPEL OVERSCHREDEN: btw van het land van de klant via OSS","onder de drempel: Belgische btw")
A16: bol.com-verkopen naar NL zijn hier niet meegeteld (land per bestelling onbekend) — Pro-count: tellen die mee voor de drempel?
